mkdocs_dracula_theme/404.html
mkdocs_dracula_theme/__init__.py
mkdocs_dracula_theme/assets/css/bootstrap.min.css
mkdocs_dracula_theme/assets/css/bootstrap.min.css.map
mkdocs_dracula_theme/assets/css/darcula-highlight.min.css
mkdocs_dracula_theme/assets/css/dracula-ui.css.map
mkdocs_dracula_theme/assets/css/dracula-ui.min.css
mkdocs_dracula_theme/assets/css/mkdocs.min.css
mkdocs_dracula_theme/assets/img/dracula.png
mkdocs_dracula_theme/assets/img/dracula.svg
mkdocs_dracula_theme/assets/img/favicon.ico
mkdocs_dracula_theme/assets/js/bootstrap.bundle.min.js
mkdocs_dracula_theme/assets/js/bootstrap.bundle.min.js.map
mkdocs_dracula_theme/assets/js/jquery-3.3.1.slim.min.js
mkdocs_dracula_theme/assets/js/mkdocs.js
mkdocs_dracula_theme/base.html
mkdocs_dracula_theme/main.html
mkdocs_dracula_theme/mkdocs_theme.yml
mkdocs_dracula_theme/modules/content.html
mkdocs_dracula_theme/modules/dropdown-menu.html
mkdocs_dracula_theme/modules/footer.html
mkdocs_dracula_theme/modules/header.html
mkdocs_dracula_theme/modules/menu.html
mkdocs_dracula_theme/modules/preview.html
mkdocs_dracula_theme/modules/sidebar.html
mkdocs_dracula_theme/modules/source.html
mkdocs_dracula_theme/search.html
mkdocs_dracula_theme/searchbox.html
mkdocs_dracula_theme-1.0.8.dist-info/LICENSE
mkdocs_dracula_theme-1.0.8.dist-info/METADATA
mkdocs_dracula_theme-1.0.8.dist-info/WHEEL
mkdocs_dracula_theme-1.0.8.dist-info/entry_points.txt
mkdocs_dracula_theme-1.0.8.dist-info/RECORD
