Metadata-Version: 2.3
Name: mkdocs-dracula-theme
Version: 1.0.8
Summary: Dark theme for Mkdocs
License: MIT License
Keywords: mkdocs,dracula,theme,dark,documentation
Author: Fernando Celmer
Author-email: email@fernandocelmer.com
Maintainer: Fernando Celmer
Maintainer-email: email@fernandocelmer.com
Requires-Python: >=3.9
Classifier: Development Status :: 4 - Beta
Classifier: Operating System :: OS Independent
Classifier: Intended Audience :: Developers
Classifier: Natural Language :: English
Classifier: Programming Language :: Python :: 3.9
Classifier: Programming Language :: Python :: 3.10
Classifier: Programming Language :: Python :: 3.11
Classifier: Programming Language :: Python :: 3.12
Classifier: Programming Language :: Python :: 3.13
Requires-Dist: mkdocs (>=1.6.1,<2.0.0)
Project-URL: Changelog, https://dracula.github.io/mkdocs/nav/development/release-notes
Project-URL: Documentation, https://dracula.github.io/mkdocs
Project-URL: Homepage, https://draculatheme.com/mkdocs
Project-URL: Issues, https://github.com/dracula/mkdocs/issues
Project-URL: Repository, https://github.com/dracula/mkdocs
